{
  "embedding_name": "network_embedding",
  "embedding_type": "network",
  "model_name": "lstm_config1",
  "model_type": "lstm",
  "embedding_mode": "network",
  "embedding_run_id": null,
  "dataset_path": "D:\\Faculty of Engineering - All Semesters\\Semester 10\\CSE489_Selected_Topics_in_Data_Science\\Projects\\sentiment-analysis-classification\\datasets\\dataset.csv",
  "dl_run_id": "660e46083f478c95",
  "dl_configuration_hash": "b9b72784b7bf305c",
  "status": "generated",
  "output_dir": "D:\\Faculty of Engineering - All Semesters\\Semester 10\\CSE489_Selected_Topics_in_Data_Science\\Projects\\sentiment-analysis-classification\\models\\dl_models\\660e46083f478c95\\network_embedding\\lstm_config1",
  "model_path": "D:\\Faculty of Engineering - All Semesters\\Semester 10\\CSE489_Selected_Topics_in_Data_Science\\Projects\\sentiment-analysis-classification\\models\\dl_models\\660e46083f478c95\\network_embedding\\lstm_config1\\model.pt",
  "predictions_path": "D:\\Faculty of Engineering - All Semesters\\Semester 10\\CSE489_Selected_Topics_in_Data_Science\\Projects\\sentiment-analysis-classification\\models\\dl_models\\660e46083f478c95\\network_embedding\\lstm_config1\\y_pred.joblib",
  "metrics": {
    "accuracy": 0.37586041299823914,
    "f1_macro": 0.22262064936646395,
    "precision_macro": 0.3645719471385627,
    "recall_macro": 0.3403861597657661
  },
  "history": [
    {
      "accuracy": 0.3728189530974868,
      "early_stopped": false,
      "early_stopping_min_delta": 0.1,
      "early_stopping_reason": null,
      "epoch": 1.0,
      "f1_macro": 0.20837721466787762,
      "overfitting_streak": 0,
      "precision_macro": 0.3450113229155747,
      "recall_macro": 0.3353721064220414,
      "train_loss": 1.0938202204789214,
      "validation_gap_exceeded_threshold": false,
      "validation_loss": 1.094445076201732,
      "validation_train_loss_gap": 0.0006248557228105689
    },
    {
      "accuracy": 0.3724987994237234,
      "early_stopped": false,
      "early_stopping_min_delta": 0.1,
      "early_stopping_reason": null,
      "epoch": 2.0,
      "f1_macro": 0.21314768469443926,
      "overfitting_streak": 0,
      "precision_macro": 0.3478484311866417,
      "recall_macro": 0.3356216817536113,
      "train_loss": 1.090797610051016,
      "validation_gap_exceeded_threshold": false,
      "validation_loss": 1.0963132903922057,
      "validation_train_loss_gap": 0.005515680341189766
    },
    {
      "accuracy": 0.373779414118777,
      "early_stopped": false,
      "early_stopping_min_delta": 0.1,
      "early_stopping_reason": null,
      "epoch": 3.0,
      "f1_macro": 0.21475134348079794,
      "overfitting_streak": 0,
      "precision_macro": 0.3639426983422418,
      "recall_macro": 0.3373585421091667,
      "train_loss": 1.083843861667304,
      "validation_gap_exceeded_threshold": false,
      "validation_loss": 1.1054537208514994,
      "validation_train_loss_gap": 0.021609859184195335
    },
    {
      "accuracy": 0.3723387225868417,
      "early_stopped": false,
      "early_stopping_min_delta": 0.1,
      "early_stopping_reason": null,
      "epoch": 4.0,
      "f1_macro": 0.20728275580856,
      "overfitting_streak": 0,
      "precision_macro": 0.3425091582803487,
      "recall_macro": 0.33523940190425683,
      "train_loss": 1.0709560628316153,
      "validation_gap_exceeded_threshold": false,
      "validation_loss": 1.115593141854544,
      "validation_train_loss_gap": 0.04463707902292868
    },
    {
      "accuracy": 0.373779414118777,
      "early_stopped": false,
      "early_stopping_min_delta": 0.1,
      "early_stopping_reason": null,
      "epoch": 5.0,
      "f1_macro": 0.21288206786880917,
      "overfitting_streak": 0,
      "precision_macro": 0.34577436986060867,
      "recall_macro": 0.3371347034994883,
      "train_loss": 1.056083532598273,
      "validation_gap_exceeded_threshold": false,
      "validation_loss": 1.1527633091841236,
      "validation_train_loss_gap": 0.0966797765858507
    },
    {
      "accuracy": 0.3734592604450136,
      "early_stopped": false,
      "early_stopping_min_delta": 0.1,
      "early_stopping_reason": null,
      "epoch": 6.0,
      "f1_macro": 0.20904881797116684,
      "overfitting_streak": 1,
      "precision_macro": 0.35226172263138195,
      "recall_macro": 0.3361685462010508,
      "train_loss": 1.046744307518387,
      "validation_gap_exceeded_threshold": true,
      "validation_loss": 1.1706923854165943,
      "validation_train_loss_gap": 0.12394807789820717
    },
    {
      "accuracy": 0.3734592604450136,
      "early_stopped": false,
      "early_stopping_min_delta": 0.1,
      "early_stopping_reason": null,
      "epoch": 7.0,
      "f1_macro": 0.2163906642550705,
      "overfitting_streak": 2,
      "precision_macro": 0.34099827792547116,
      "recall_macro": 0.33700013275789203,
      "train_loss": 1.040986640037764,
      "validation_gap_exceeded_threshold": true,
      "validation_loss": 1.193411768618175,
      "validation_train_loss_gap": 0.15242512858041102
    },
    {
      "accuracy": 0.37586041299823914,
      "early_stopped": true,
      "early_stopping_min_delta": 0.1,
      "early_stopping_reason": "validation_loss_gap_exceeded_threshold",
      "epoch": 8.0,
      "f1_macro": 0.22262064936646395,
      "overfitting_streak": 3,
      "precision_macro": 0.3645719471385627,
      "recall_macro": 0.3403861597657661,
      "train_loss": 1.0375288184557006,
      "validation_gap_exceeded_threshold": true,
      "validation_loss": 1.1902597333138059,
      "validation_train_loss_gap": 0.1527309148581053
    }
  ],
  "parameters": {
    "activation_functions": [
      "relu"
    ],
    "batch_size": 64,
    "bidirectional": true,
    "dropout": 0.3,
    "early_stopping_min_delta": 0.1,
    "early_stopping_patience": 3,
    "embedding_mode": "network",
    "epochs": 20,
    "hidden_dim": 128,
    "hidden_dims": [
      128,
      64
    ],
    "hidden_layers": 2,
    "learning_rate": 0.001,
    "max_sequence_length": 64,
    "max_vocab_size": 30000,
    "model_type": "lstm",
    "num_hidden_states": 128,
    "token_embedding_dim": 100,
    "weight_decay": 0.0001
  },
  "configured_parameters": {
    "batch_size": 64,
    "bidirectional": true,
    "config_name": "config1",
    "dropout": 0.3,
    "early_stopping_min_delta": 0.1,
    "early_stopping_patience": 3,
    "embedding_mode": "network",
    "epochs": 20,
    "hidden_dims": [
      128,
      64
    ],
    "learning_rate": 0.001,
    "max_sequence_length": 64,
    "max_vocab_size": 30000,
    "name": "lstm_config1",
    "token_embedding_dim": 100,
    "type": "lstm",
    "weight_decay": 0.0001
  },
  "device": "cuda",
  "cuda_device_name": "NVIDIA GeForce RTX 3060 Laptop GPU",
  "train_shape": [
    24985,
    64
  ],
  "test_shape": [
    6247,
    64
  ],
  "classes": [
    "0",
    "1",
    "2"
  ],
  "metadata_path": "D:\\Faculty of Engineering - All Semesters\\Semester 10\\CSE489_Selected_Topics_in_Data_Science\\Projects\\sentiment-analysis-classification\\models\\dl_models\\660e46083f478c95\\network_embedding\\lstm_config1\\metadata.json"
}